serial_adder.v
module serial_adder (clk, rst, x, y, z);
input clk, rst, x, y;
output reg z;
parameter s0 = 0, s1 = 1;
reg PS,NS;
always @(posedge clk, posedge rst) begin
    if(rst) PS <= s0;
    else PS <= NS;
end

always @(PS, x, y) begin
    case (PS)
    s0 : begin
        if({x,y} == 0) begin NS = s0; z = 0; end
        else if({x,y} == 1) begin NS = s0; z =1; end 
        else if({x,y} == 2) begin NS = s0; z = 1; end 
        else if({x,y} == 3) begin NS = s1; z = 0; end 
    end
    s1 : begin
        if({x,y} == 0) begin NS = s0; z = 1; end
        else if({x,y} == 1) begin NS = s1; z =0; end 
        else if({x,y} == 2) begin NS = s1; z = 0; end 
        else if({x,y} == 3)begin NS = s1; z = 1; end  
    end
    default : begin NS = s0; z = 0; end
    endcase
end
    
endmodule

serial_adder_tb.v
module testbench;
reg clk, rst, x, y;
wire z;

serial_adder DUT(clk, rst, x, y, z);

initial begin
    clk = 1'b0;
    rst = 1'b1;
    #15 rst = 1'b0;
end

always #5 clk = ~ clk;

initial begin
    $dumpfile("serial_adder.vcd");
    $dumpvars(0, testbench);
    $monitor($time , " x = %b y = %b z = %b ", x,y,z);
    #12 x = 0; y = 0; #10 x = 1; y = 1; #10 x = 1; y = 0; #10 x = 0; y = 1;
    #10 x = 1; y = 1; #10 x = 0; y = 0; #10 x = 1; y = 0; #10 x = 1; y = 1;
    #200 $finish;
end
endmodule

serial_adder.vcd
$date
	Sun May 23 15:29:08 2021
$end
$version
	Icarus Verilog
$end
$timescale
	1s
$end
$scope module testbench $end
$var wire 1 ! z $end
$var reg 1 " clk $end
$var reg 1 # rst $end
$var reg 1 $ x $end
$var reg 1 % y $end
$scope module DUT $end
$var wire 1 " clk $end
$var wire 1 # rst $end
$var wire 1 $ x $end
$var wire 1 % y $end
$var reg 1 & NS $end
$var reg 1 ' PS $end
$var reg 1 ! z $end
$upscope $end
$upscope $end
$enddefinitions $end
#0
$dumpvars
0'
x&
x%
x$
1#
0"
x!
$end
#5
1"
#10
0"
#12
0!
0&
0%
0$
#15
1"
0#
#20
0"
#22
1&
1%
1$
#25
1!
1'
1"
#30
0"
#32
0!
0%
#35
1"
#40
0"
#42
1%
0$
#45
1"
#50
0"
#52
1!
1$
#55
1"
#60
0"
#62
0&
0%
0$
#65
0!
0'
1"
#70
0"
#72
1!
1$
#75
1"
#80
0"
#82
0!
1&
1%
#85
1!
1'
1"
